vsoneliner/__init__.py
vsoneliner/__main__.py
vsoneliner/vsoneliner.py
vsoneliner-0.0.2.post1.dist-info/METADATA
vsoneliner-0.0.2.post1.dist-info/WHEEL
vsoneliner-0.0.2.post1.dist-info/licenses/LICENSE
vsoneliner-0.0.2.post1.dist-info/RECORD
