Metadata-Version: 2.4
Name: vsoneliner
Version: 0.0.2.post1
Summary: Commandline program for creating Python script for VSPipe
Project-URL: Documentation, https://github.com/Akatmks/vsoneliner
Project-URL: Issues, https://github.com/Akatmks/vsoneliner/issues
Project-URL: Source, https://github.com/Akatmks/vsoneliner
Author-email: Akatsumekusa <Akatsumekusa@protonmail.com>
License-Expression: MIT
License-File: LICENSE
Keywords: VapourSynth
Classifier: License :: OSI Approved :: MIT License
Classifier: Programming Language :: Python
Classifier: Programming Language :: Python :: 3.12
Classifier: Programming Language :: Python :: 3.13
Classifier: Topic :: Multimedia :: Video
Requires-Python: >=3
Requires-Dist: coconut
